torchmetrics_ext/__init__.py
torchmetrics_ext/metrics/__init__.py
torchmetrics_ext/metrics/object_detection/__init__.py
torchmetrics_ext/metrics/object_detection/mean_average_precision_3d.py
torchmetrics_ext/metrics/visual_grounding/__init__.py
torchmetrics_ext/metrics/visual_grounding/multi3drefer.py
torchmetrics_ext/metrics/visual_grounding/nr3d.py
torchmetrics_ext/metrics/visual_grounding/scanrefer.py
torchmetrics_ext/metrics/visual_grounding/vigil3d.py
torchmetrics_ext/tools/__init__.py
torchmetrics_ext/tools/bounding_box_3d.py
torchmetrics_ext-0.3.1.dist-info/licenses/LICENSE
torchmetrics_ext-0.3.1.dist-info/METADATA
torchmetrics_ext-0.3.1.dist-info/WHEEL
torchmetrics_ext-0.3.1.dist-info/top_level.txt
torchmetrics_ext-0.3.1.dist-info/RECORD
