Metadata-Version: 2.4
Name: torchmetrics_ext
Version: 0.3.1
Summary: An extension of torchmetrics package.
Home-page: https://github.com/eamonn-zh/torchmetrics_ext
Author: Yiming Zhang
Keywords: deep learning,machine learning,pytorch,metrics
Classifier: Natural Language :: English
Classifier: Development Status :: 4 - Beta
Classifier: License :: OSI Approved :: Apache Software License
Classifier: Intended Audience :: Developers
Classifier: Topic :: Scientific/Engineering :: Artificial Intelligence
Classifier: Operating System :: OS Independent
Classifier: Programming Language :: Python :: 3
Requires-Python: >=3.8
License-File: LICENSE
Requires-Dist: torchmetrics
Requires-Dist: torch
Requires-Dist: huggingface_hub
Requires-Dist: datasets
Requires-Dist: scipy
Requires-Dist: gdown
Provides-Extra: dev
Requires-Dist: pytest; extra == "dev"
Dynamic: author
Dynamic: classifier
Dynamic: description
Dynamic: description-content-type
Dynamic: home-page
Dynamic: keywords
Dynamic: license-file
Dynamic: provides-extra
Dynamic: requires-dist
Dynamic: requires-python
Dynamic: summary
